fastcrudapi/__init__.py
fastcrudapi/builder.py
fastcrudapi/core.py
fastcrudapi-0.1.4.dist-info/LICENSE
fastcrudapi-0.1.4.dist-info/METADATA
fastcrudapi-0.1.4.dist-info/WHEEL
fastcrudapi-0.1.4.dist-info/RECORD
