Metadata-Version: 2.1
Name: fastcrudapi
Version: 0.1.4
Summary: The package helps to build CRUD APIs for models based on FastAPI.
Author: lpthong90
Author-email: lpthong90@gmail.com
Requires-Python: >=3.8,<4.0
Classifier: Programming Language :: Python :: 3
Classifier: Programming Language :: Python :: 3.8
Classifier: Programming Language :: Python :: 3.9
Classifier: Programming Language :: Python :: 3.10
Classifier: Programming Language :: Python :: 3.11
Classifier: Programming Language :: Python :: 3.12
Provides-Extra: sqlalchemy
Provides-Extra: sqlmodel
Requires-Dist: fastapi (>=0.108.0,<0.109.0)
